ybdata/__init__.py
ybdata/__main__.py
ybdata/app.py
ybdata/utils.py
ybdata/validate.py
ybdata/version.py
ybdata/commands/__init__.py
ybdata/commands/convert.py
ybdata/commands/list.py
ybdata/commands/package.py
ybdata/commands/upload.py
ybdata/commands/validate.py
yellowbrick_datasets-1.0.dist-info/LICENSE.txt
yellowbrick_datasets-1.0.dist-info/METADATA
yellowbrick_datasets-1.0.dist-info/WHEEL
yellowbrick_datasets-1.0.dist-info/entry_points.txt
yellowbrick_datasets-1.0.dist-info/top_level.txt
yellowbrick_datasets-1.0.dist-info/zip-safe
yellowbrick_datasets-1.0.dist-info/RECORD
