Metadata-Version: 2.1
Name: yellowbrick-datasets
Version: 1.0
Summary: Yellowbrick datasets management and deployment scripts.
Home-page: https://github.com/districtdatalabs/yellowbrick-datasets
Author: Rebecca Bilbro, Benjamin Bengfort
Author-email: yellowbrick@googlegroups.com
Maintainer: Benjamin Bengfort
Maintainer-email: yellowbrick@googlegroups.com
License: Apache 2
Download-URL: https://github.com/districtdatalabs/yellowbrick-datasets/tarball/v1.0
Keywords: datasets,machine learning,scikit-learn,matplotlib,data science
Platform: UNKNOWN
Classifier: Development Status :: 4 - Beta
Classifier: Intended Audience :: Developers
Classifier: Intended Audience :: Science/Research
Classifier: License :: OSI Approved :: Apache Software License
Classifier: Natural Language :: English
Classifier: Operating System :: OS Independent
Classifier: Programming Language :: Python
Classifier: Programming Language :: Python :: 3.6
Classifier: Topic :: Software Development
Classifier: Topic :: Software Development :: Libraries :: Python Modules
Requires-Python: >=3.4
Requires-Dist: boto3 (==1.9.71)
Requires-Dist: commis (==0.4)
Requires-Dist: numpy (==1.15.4)
Requires-Dist: pandas (==0.23.4)
Requires-Dist: tabulate (==0.8.2)
Requires-Dist: tqdm (==4.28.1)
